<?xml version="1.0" encoding="UTF-8" ?>

<!-- * tiles.xml * * Copyright (C) 2017 Universidad de Sevilla * * The use 
	of this project is hereby constrained to the conditions of the * TDG Licence, 
	a copy of which you may download from * http://www.tdg-seville.info/License.html -->

<!DOCTYPE tiles-definitions PUBLIC
       "-//Apache Software Foundation//DTD Tiles Configuration 2.0//EN"
       "http://tiles.apache.org/dtds/tiles-config_2_0.dtd">

<tiles-definitions>

	<definition name="schoolCalendar/list" extends="master.page">
		<put-attribute name="title" value="School Calendars" />
		<put-attribute name="body" value="/views/schoolCalendar/list.jsp" />
	</definition>
	<definition name="schoolCalendar/display" extends="master.page">
		<put-attribute name="title" value="School Calendar" />
		<put-attribute name="body" value="/views/schoolCalendar/display.jsp" />
	</definition>
	<definition name="schoolCalendar/parent/link" extends="master.page">
		<put-attribute name="title" value="Link School Calendar" />
		<put-attribute name="body" value="/views/schoolCalendar/link.jsp" />
	</definition>
	<definition name="schoolCalendar/administrator/create" extends="master.page">
		<put-attribute name="title" value="Create School Calendar" />
		<put-attribute name="body" value="/views/schoolCalendar/create.jsp" />
	</definition>
	<definition name="schoolCalendar/administrator/edit" extends="master.page">
		<put-attribute name="title" value="School Calendar Edition" />
		<put-attribute name="body" value="/views/schoolCalendar/create.jsp" />
	</definition>

</tiles-definitions>